{
  "total": 53,
  "total_pages": 6,
  "results": [
    {
      "id": "oXV3bzR7jxI",
      "created_at": "2018-08-18T22:02:43-04:00",
      "updated_at": "2018-08-29T10:10:38-04:00",
      "width": 5616,
      "height": 3744,
      "color": "#0D0709",
      "description": "person using pencil",
      "urls": {
        "raw": "https://images.unsplash.com/photo-1534644107580-3a4dbd494a95?ixlib=rb-1.2.1&ixid=eyJhcHBfaWQiOjUyNzA0fQ",
        "full": "https://images.unsplash.com/photo-1534644107580-3a4dbd494a95?ixlib=rb-1.2.1&q=85&fm=jpg&crop=entropy&cs=srgb&ixid=eyJhcHBfaWQiOjUyNzA0fQ",
        "regular": "https://images.unsplash.com/photo-1534644107580-3a4dbd494a95?ixlib=rb-1.2.1&q=80&fm=jpg&crop=entropy&cs=tinysrgb&w=1080&fit=max&ixid=eyJhcHBfaWQiOjUyNzA0fQ",
        "small": "https://images.unsplash.com/photo-1534644107580-3a4dbd494a95?ixlib=rb-1.2.1&q=80&fm=jpg&crop=entropy&cs=tinysrgb&w=400&fit=max&ixid=eyJhcHBfaWQiOjUyNzA0fQ",
        "thumb": "https://images.unsplash.com/photo-1534644107580-3a4dbd494a95?ixlib=rb-1.2.1&q=80&fm=jpg&crop=entropy&cs=tinysrgb&w=200&fit=max&ixid=eyJhcHBfaWQiOjUyNzA0fQ"
      },
      "links": {
        "self": "https://api.unsplash.com/photos/oXV3bzR7jxI",
        "html": "https://unsplash.com/photos/oXV3bzR7jxI",
        "download": "https://unsplash.com/photos/oXV3bzR7jxI/download",
        "download_location": "https://api.unsplash.com/photos/oXV3bzR7jxI/download"
      },
      "categories": [],
      "sponsored": false,
      "sponsored_by": null,
      "sponsored_impressions_id": null,
      "likes": 50,
      "liked_by_user": false,
      "current_user_collections": [],
      "slug": "fourth-grade-learning-right-handed",
      "user": {
        "id": "OPWnATs4eK8",
        "updated_at": "2019-01-15T18:59:18-05:00",
        "username": "benmullins",
        "name": "Ben Mullins",
        "first_name": "Ben",
        "last_name": "Mullins",
        "twitter_username": null,
        "portfolio_url": null,
        "bio": null,
        "location": null,
        "links": {
          "self": "https://api.unsplash.com/users/benmullins",
          "html": "https://unsplash.com/@benmullins",
          "photos": "https://api.unsplash.com/users/benmullins/photos",
          "likes": "https://api.unsplash.com/users/benmullins/likes",
          "portfolio": "https://api.unsplash.com/users/benmullins/portfolio",
          "following": "https://api.unsplash.com/users/benmullins/following",
          "followers": "https://api.unsplash.com/users/benmullins/followers"
        },
        "profile_image": {
          "small": "https://images.unsplash.com/profile-fb-1532554354-976587e56fb0.jpg?ixlib=rb-1.2.1&q=80&fm=jpg&crop=faces&cs=tinysrgb&fit=crop&h=32&w=32",
          "medium": "https://images.unsplash.com/profile-fb-1532554354-976587e56fb0.jpg?ixlib=rb-1.2.1&q=80&fm=jpg&crop=faces&cs=tinysrgb&fit=crop&h=64&w=64",
          "large": "https://images.unsplash.com/profile-fb-1532554354-976587e56fb0.jpg?ixlib=rb-1.2.1&q=80&fm=jpg&crop=faces&cs=tinysrgb&fit=crop&h=128&w=128"
        },
        "instagram_username": null,
        "total_collections": 0,
        "total_likes": 21,
        "total_photos": 22,
        "accepted_tos": false
      },
      "tags": [
        {
          "title": "pen"
        },
        {
          "title": "hand"
        },
        {
          "title": "draw"
        },
        {
          "title": "write"
        },
        {
          "title": "learn"
        },
        {
          "title": "study"
        },
        {
          "title": "table"
        },
        {
          "title": "person"
        },
        {
          "title": "student"
        },
        {
          "title": "college"
        },
        {
          "title": "school"
        },
        {
          "title": "right handed"
        },
        {
          "title": "fourth grade"
        },
        {
          "title": "learning"
        }
      ],
      "photo_tags": [
        {
          "title": "pen"
        },
        {
          "title": "hand"
        },
        {
          "title": "draw"
        },
        {
          "title": "write"
        },
        {
          "title": "learn"
        }
      ]
    },
    {
      "id": "TC5P6ZRxDbI",
      "created_at": "2018-09-13T17:52:36-04:00",
      "updated_at": "2018-11-20T14:01:20-05:00",
      "width": 3450,
      "height": 2285,
      "color": "#131618",
      "description": "two person using MacBook and holding pencil",
      "urls": {
        "raw": "https://images.unsplash.com/photo-1536875489903-655d152ed785?ixlib=rb-1.2.1&ixid=eyJhcHBfaWQiOjUyNzA0fQ",
        "full": "https://images.unsplash.com/photo-1536875489903-655d152ed785?ixlib=rb-1.2.1&q=85&fm=jpg&crop=entropy&cs=srgb&ixid=eyJhcHBfaWQiOjUyNzA0fQ",
        "regular": "https://images.unsplash.com/photo-1536875489903-655d152ed785?ixlib=rb-1.2.1&q=80&fm=jpg&crop=entropy&cs=tinysrgb&w=1080&fit=max&ixid=eyJhcHBfaWQiOjUyNzA0fQ",
        "small": "https://images.unsplash.com/photo-1536875489903-655d152ed785?ixlib=rb-1.2.1&q=80&fm=jpg&crop=entropy&cs=tinysrgb&w=400&fit=max&ixid=eyJhcHBfaWQiOjUyNzA0fQ",
        "thumb": "https://images.unsplash.com/photo-1536875489903-655d152ed785?ixlib=rb-1.2.1&q=80&fm=jpg&crop=entropy&cs=tinysrgb&w=200&fit=max&ixid=eyJhcHBfaWQiOjUyNzA0fQ"
      },
      "links": {
        "self": "https://api.unsplash.com/photos/TC5P6ZRxDbI",
        "html": "https://unsplash.com/photos/TC5P6ZRxDbI",
        "download": "https://unsplash.com/photos/TC5P6ZRxDbI/download",
        "download_location": "https://api.unsplash.com/photos/TC5P6ZRxDbI/download"
      },
      "categories": [],
      "sponsored": false,
      "sponsored_by": null,
      "sponsored_impressions_id": null,
      "likes": 13,
      "liked_by_user": false,
      "current_user_collections": [],
      "slug": "feedback-user-experience-research",
      "user": {
        "id": "n5jFmhLyfYw",
        "updated_at": "2019-01-15T18:59:18-05:00",
        "username": "alecuffia",
        "name": "José Alejandro Cuffia",
        "first_name": "José Alejandro",
        "last_name": "Cuffia",
        "twitter_username": "alecuffia",
        "portfolio_url": "https://www.instagram.com/alecuffia",
        "bio": "Photographer and UX/UI Designer",
        "location": "Buenos Aires, Argentina",
        "links": {
          "self": "https://api.unsplash.com/users/alecuffia",
          "html": "https://unsplash.com/@alecuffia",
          "photos": "https://api.unsplash.com/users/alecuffia/photos",
          "likes": "https://api.unsplash.com/users/alecuffia/likes",
          "portfolio": "https://api.unsplash.com/users/alecuffia/portfolio",
          "following": "https://api.unsplash.com/users/alecuffia/following",
          "followers": "https://api.unsplash.com/users/alecuffia/followers"
        },
        "profile_image": {
          "small": "https://images.unsplash.com/profile-1539701465756-26b323a67a38?ixlib=rb-1.2.1&q=80&fm=jpg&crop=faces&cs=tinysrgb&fit=crop&h=32&w=32",
          "medium": "https://images.unsplash.com/profile-1539701465756-26b323a67a38?ixlib=rb-1.2.1&q=80&fm=jpg&crop=faces&cs=tinysrgb&fit=crop&h=64&w=64",
          "large": "https://images.unsplash.com/profile-1539701465756-26b323a67a38?ixlib=rb-1.2.1&q=80&fm=jpg&crop=faces&cs=tinysrgb&fit=crop&h=128&w=128"
        },
        "instagram_username": "alecuffia",
        "total_collections": 0,
        "total_likes": 3,
        "total_photos": 68,
        "accepted_tos": true
      },
      "tags": [
        {
          "title": "book"
        },
        {
          "title": "pencil"
        },
        {
          "title": "computer"
        },
        {
          "title": "laptop"
        },
        {
          "title": "table"
        },
        {
          "title": "write"
        },
        {
          "title": "notes"
        },
        {
          "title": "notebook"
        },
        {
          "title": "workspace"
        },
        {
          "title": "meeting"
        },
        {
          "title": "type"
        },
        {
          "title": "tech"
        },
        {
          "title": "technology"
        },
        {
          "title": "desk"
        },
        {
          "title": "feedback"
        },
        {
          "title": "user experience"
        },
        {
          "title": "research"
        },
        {
          "title": "hand"
        },
        {
          "title": "close up"
        },
        {
          "title": "interview"
        }
      ],
      "photo_tags": [
        {
          "title": "book"
        },
        {
          "title": "pencil"
        },
        {
          "title": "computer"
        },
        {
          "title": "laptop"
        },
        {
          "title": "table"
        }
      ]
    },
    {
      "id": "ViEBSoZH6M4",
      "created_at": "2018-02-08T18:52:27-05:00",
      "updated_at": "2018-08-28T20:46:38-04:00",
      "width": 3024,
      "height": 4032,
      "color": "#020B1B",
      "description": "brown pencil on equation paper",
      "urls": {
        "raw": "https://images.unsplash.com/photo-1518133910546-b6c2fb7d79e3?ixlib=rb-1.2.1&ixid=eyJhcHBfaWQiOjUyNzA0fQ",
        "full": "https://images.unsplash.com/photo-1518133910546-b6c2fb7d79e3?ixlib=rb-1.2.1&q=85&fm=jpg&crop=entropy&cs=srgb&ixid=eyJhcHBfaWQiOjUyNzA0fQ",
        "regular": "https://images.unsplash.com/photo-1518133910546-b6c2fb7d79e3?ixlib=rb-1.2.1&q=80&fm=jpg&crop=entropy&cs=tinysrgb&w=1080&fit=max&ixid=eyJhcHBfaWQiOjUyNzA0fQ",
        "small": "https://images.unsplash.com/photo-1518133910546-b6c2fb7d79e3?ixlib=rb-1.2.1&q=80&fm=jpg&crop=entropy&cs=tinysrgb&w=400&fit=max&ixid=eyJhcHBfaWQiOjUyNzA0fQ",
        "thumb": "https://images.unsplash.com/photo-1518133910546-b6c2fb7d79e3?ixlib=rb-1.2.1&q=80&fm=jpg&crop=entropy&cs=tinysrgb&w=200&fit=max&ixid=eyJhcHBfaWQiOjUyNzA0fQ"
      },
      "links": {
        "self": "https://api.unsplash.com/photos/ViEBSoZH6M4",
        "html": "https://unsplash.com/photos/ViEBSoZH6M4",
        "download": "https://unsplash.com/photos/ViEBSoZH6M4/download",
        "download_location": "https://api.unsplash.com/photos/ViEBSoZH6M4/download"
      },
      "categories": [],
      "sponsored": false,
      "sponsored_by": null,
      "sponsored_impressions_id": null,
      "likes": 78,
      "liked_by_user": false,
      "current_user_collections": [],
      "slug": "math-exam",
      "user": {
        "id": "vm7k_1iG2Jw",
        "updated_at": "2019-01-22T08:56:08-05:00",
        "username": "chrisliverani",
        "name": "Chris Liverani",
        "first_name": "Chris",
        "last_name": "Liverani",
        "twitter_username": "chrisliverani",
        "portfolio_url": null,
        "bio": "Unsplash numbers guy // student at the @charlesdeluvio school of photography",
        "location": "Montreal, QC",
        "links": {
          "self": "https://api.unsplash.com/users/chrisliverani",
          "html": "https://unsplash.com/@chrisliverani",
          "photos": "https://api.unsplash.com/users/chrisliverani/photos",
          "likes": "https://api.unsplash.com/users/chrisliverani/likes",
          "portfolio": "https://api.unsplash.com/users/chrisliverani/portfolio",
          "following": "https://api.unsplash.com/users/chrisliverani/following",
          "followers": "https://api.unsplash.com/users/chrisliverani/followers"
        },
        "profile_image": {
          "small": "https://images.unsplash.com/profile-1542390524643-c5053b52fc98?ixlib=rb-1.2.1&q=80&fm=jpg&crop=faces&cs=tinysrgb&fit=crop&h=32&w=32",
          "medium": "https://images.unsplash.com/profile-1542390524643-c5053b52fc98?ixlib=rb-1.2.1&q=80&fm=jpg&crop=faces&cs=tinysrgb&fit=crop&h=64&w=64",
          "large": "https://images.unsplash.com/profile-1542390524643-c5053b52fc98?ixlib=rb-1.2.1&q=80&fm=jpg&crop=faces&cs=tinysrgb&fit=crop&h=128&w=128"
        },
        "instagram_username": null,
        "total_collections": 2,
        "total_likes": 200,
        "total_photos": 100,
        "accepted_tos": true
      },
      "tags": [
        {
          "title": "pencil"
        },
        {
          "title": "paper"
        },
        {
          "title": "math"
        },
        {
          "title": "problem"
        },
        {
          "title": "multiplication"
        },
        {
          "title": "task"
        },
        {
          "title": "shadow"
        },
        {
          "title": "exam"
        },
        {
          "title": "question"
        },
        {
          "title": "number"
        },
        {
          "title": "school"
        },
        {
          "title": "mathematic"
        },
        {
          "title": "mathematics task"
        }
      ],
      "photo_tags": [
        {
          "title": "pencil"
        },
        {
          "title": "paper"
        },
        {
          "title": "math"
        },
        {
          "title": "problem"
        },
        {
          "title": "multiplication"
        }
      ]
    },
    {
      "id": "WC6MJ0kRzGw",
      "created_at": "2018-02-11T06:48:34-05:00",
      "updated_at": "2018-08-28T20:47:06-04:00",
      "width": 2560,
      "height": 1707,
      "color": "#47212B",
      "description": "person holding pink sticky note",
      "urls": {
        "raw": "https://images.unsplash.com/photo-1518349619113-03114f06ac3a?ixlib=rb-1.2.1&ixid=eyJhcHBfaWQiOjUyNzA0fQ",
        "full": "https://images.unsplash.com/photo-1518349619113-03114f06ac3a?ixlib=rb-1.2.1&q=85&fm=jpg&crop=entropy&cs=srgb&ixid=eyJhcHBfaWQiOjUyNzA0fQ",
        "regular": "https://images.unsplash.com/photo-1518349619113-03114f06ac3a?ixlib=rb-1.2.1&q=80&fm=jpg&crop=entropy&cs=tinysrgb&w=1080&fit=max&ixid=eyJhcHBfaWQiOjUyNzA0fQ",
        "small": "https://images.unsplash.com/photo-1518349619113-03114f06ac3a?ixlib=rb-1.2.1&q=80&fm=jpg&crop=entropy&cs=tinysrgb&w=400&fit=max&ixid=eyJhcHBfaWQiOjUyNzA0fQ",
        "thumb": "https://images.unsplash.com/photo-1518349619113-03114f06ac3a?ixlib=rb-1.2.1&q=80&fm=jpg&crop=entropy&cs=tinysrgb&w=200&fit=max&ixid=eyJhcHBfaWQiOjUyNzA0fQ"
      },
      "links": {
        "self": "https://api.unsplash.com/photos/WC6MJ0kRzGw",
        "html": "https://unsplash.com/photos/WC6MJ0kRzGw",
        "download": "https://unsplash.com/photos/WC6MJ0kRzGw/download",
        "download_location": "https://api.unsplash.com/photos/WC6MJ0kRzGw/download"
      },
      "categories": [],
      "sponsored": false,
      "sponsored_by": null,
      "sponsored_impressions_id": null,
      "likes": 189,
      "liked_by_user": false,
      "current_user_collections": [],
      "slug": "run-a-usability-test",
      "user": {
        "id": "SMN9a89ULnc",
        "updated_at": "2019-01-15T18:59:17-05:00",
        "username": "dtravisphd",
        "name": "David Travis",
        "first_name": "David",
        "last_name": "Travis",
        "twitter_username": null,
        "portfolio_url": null,
        "bio": null,
        "location": null,
        "links": {
          "self": "https://api.unsplash.com/users/dtravisphd",
          "html": "https://unsplash.com/@dtravisphd",
          "photos": "https://api.unsplash.com/users/dtravisphd/photos",
          "likes": "https://api.unsplash.com/users/dtravisphd/likes",
          "portfolio": "https://api.unsplash.com/users/dtravisphd/portfolio",
          "following": "https://api.unsplash.com/users/dtravisphd/following",
          "followers": "https://api.unsplash.com/users/dtravisphd/followers"
        },
        "profile_image": {
          "small": "https://images.unsplash.com/profile-fb-1515915632-e88a3ca2c78c.jpg?ixlib=rb-1.2.1&q=80&fm=jpg&crop=faces&cs=tinysrgb&fit=crop&h=32&w=32",
          "medium": "https://images.unsplash.com/profile-fb-1515915632-e88a3ca2c78c.jpg?ixlib=rb-1.2.1&q=80&fm=jpg&crop=faces&cs=tinysrgb&fit=crop&h=64&w=64",
          "large": "https://images.unsplash.com/profile-fb-1515915632-e88a3ca2c78c.jpg?ixlib=rb-1.2.1&q=80&fm=jpg&crop=faces&cs=tinysrgb&fit=crop&h=128&w=128"
        },
        "instagram_username": null,
        "total_collections": 5,
        "total_likes": 3,
        "total_photos": 6,
        "accepted_tos": false
      },
      "tags": [
        {
          "title": "note"
        },
        {
          "title": "post it"
        },
        {
          "title": "pink"
        },
        {
          "title": "paper"
        },
        {
          "title": "hand"
        },
        {
          "title": "holding"
        },
        {
          "title": "office"
        },
        {
          "title": "wall"
        },
        {
          "title": "work space"
        },
        {
          "title": "work"
        },
        {
          "title": "grid"
        },
        {
          "title": "user research"
        },
        {
          "title": "user experience"
        },
        {
          "title": "ux"
        },
        {
          "title": "writing"
        },
        {
          "title": "sticky"
        },
        {
          "title": "post-it"
        },
        {
          "title": "usability"
        }
      ],
      "photo_tags": [
        {
          "title": "note"
        },
        {
          "title": "post it"
        },
        {
          "title": "pink"
        },
        {
          "title": "paper"
        },
        {
          "title": "hand"
        }
      ]
    },
    {
      "id": "pwcKF7L4-no",
      "created_at": "2018-07-21T11:47:40-04:00",
      "updated_at": "2018-08-28T21:16:10-04:00",
      "width": 5184,
      "height": 3456,
      "color": "#F5F0EB",
      "description": "refill of liquid on tubes",
      "urls": {
        "raw": "https://images.unsplash.com/photo-1532187863486-abf9dbad1b69?ixlib=rb-1.2.1&ixid=eyJhcHBfaWQiOjUyNzA0fQ",
        "full": "https://images.unsplash.com/photo-1532187863486-abf9dbad1b69?ixlib=rb-1.2.1&q=85&fm=jpg&crop=entropy&cs=srgb&ixid=eyJhcHBfaWQiOjUyNzA0fQ",
        "regular": "https://images.unsplash.com/photo-1532187863486-abf9dbad1b69?ixlib=rb-1.2.1&q=80&fm=jpg&crop=entropy&cs=tinysrgb&w=1080&fit=max&ixid=eyJhcHBfaWQiOjUyNzA0fQ",
        "small": "https://images.unsplash.com/photo-1532187863486-abf9dbad1b69?ixlib=rb-1.2.1&q=80&fm=jpg&crop=entropy&cs=tinysrgb&w=400&fit=max&ixid=eyJhcHBfaWQiOjUyNzA0fQ",
        "thumb": "https://images.unsplash.com/photo-1532187863486-abf9dbad1b69?ixlib=rb-1.2.1&q=80&fm=jpg&crop=entropy&cs=tinysrgb&w=200&fit=max&ixid=eyJhcHBfaWQiOjUyNzA0fQ"
      },
      "links": {
        "self": "https://api.unsplash.com/photos/pwcKF7L4-no",
        "html": "https://unsplash.com/photos/pwcKF7L4-no",
        "download": "https://unsplash.com/photos/pwcKF7L4-no/download",
        "download_location": "https://api.unsplash.com/photos/pwcKF7L4-no/download"
      },
      "categories": [],
      "sponsored": false,
      "sponsored_by": null,
      "sponsored_impressions_id": null,
      "likes": 95,
      "liked_by_user": false,
      "current_user_collections": [],
      "slug": "purple-pipette",
      "user": {
        "id": "4BYRpKXv3o0",
        "updated_at": "2019-01-20T04:06:01-05:00",
        "username": "_louisreed",
        "name": "Louis Reed",
        "first_name": "Louis",
        "last_name": "Reed",
        "twitter_username": "_LouisReed",
        "portfolio_url": "https://www.louisreed.co.uk",
        "bio": null,
        "location": null,
        "links": {
          "self": "https://api.unsplash.com/users/_louisreed",
          "html": "https://unsplash.com/@_louisreed",
          "photos": "https://api.unsplash.com/users/_louisreed/photos",
          "likes": "https://api.unsplash.com/users/_louisreed/likes",
          "portfolio": "https://api.unsplash.com/users/_louisreed/portfolio",
          "following": "https://api.unsplash.com/users/_louisreed/following",
          "followers": "https://api.unsplash.com/users/_louisreed/followers"
        },
        "profile_image": {
          "small": "https://images.unsplash.com/profile-1532019023716-da3f551a6034?ixlib=rb-1.2.1&q=80&fm=jpg&crop=faces&cs=tinysrgb&fit=crop&h=32&w=32",
          "medium": "https://images.unsplash.com/profile-1532019023716-da3f551a6034?ixlib=rb-1.2.1&q=80&fm=jpg&crop=faces&cs=tinysrgb&fit=crop&h=64&w=64",
          "large": "https://images.unsplash.com/profile-1532019023716-da3f551a6034?ixlib=rb-1.2.1&q=80&fm=jpg&crop=faces&cs=tinysrgb&fit=crop&h=128&w=128"
        },
        "instagram_username": null,
        "total_collections": 13,
        "total_likes": 30,
        "total_photos": 83,
        "accepted_tos": true
      },
      "tags": [
        {
          "title": "research"
        },
        {
          "title": "laboratory"
        },
        {
          "title": "test tube"
        },
        {
          "title": "science"
        },
        {
          "title": "pipette"
        },
        {
          "title": "liquid"
        },
        {
          "title": "purple"
        },
        {
          "title": "science experiment"
        }
      ],
      "photo_tags": [
        {
          "title": "research"
        },
        {
          "title": "laboratory"
        },
        {
          "title": "test tube"
        },
        {
          "title": "science"
        },
        {
          "title": "pipette"
        }
      ]
    },
    {
      "id": "pQwll5IG-I0",
      "created_at": "2018-01-23T23:28:06-05:00",
      "updated_at": "2018-08-28T20:41:56-04:00",
      "width": 2988,
      "height": 5312,
      "color": "#0C192D",
      "description": "cactus succulent plant on white vase",
      "urls": {
        "raw": "https://images.unsplash.com/photo-1516767848735-fb701beb5567?ixlib=rb-1.2.1&ixid=eyJhcHBfaWQiOjUyNzA0fQ",
        "full": "https://images.unsplash.com/photo-1516767848735-fb701beb5567?ixlib=rb-1.2.1&q=85&fm=jpg&crop=entropy&cs=srgb&ixid=eyJhcHBfaWQiOjUyNzA0fQ",
        "regular": "https://images.unsplash.com/photo-1516767848735-fb701beb5567?ixlib=rb-1.2.1&q=80&fm=jpg&crop=entropy&cs=tinysrgb&w=1080&fit=max&ixid=eyJhcHBfaWQiOjUyNzA0fQ",
        "small": "https://images.unsplash.com/photo-1516767848735-fb701beb5567?ixlib=rb-1.2.1&q=80&fm=jpg&crop=entropy&cs=tinysrgb&w=400&fit=max&ixid=eyJhcHBfaWQiOjUyNzA0fQ",
        "thumb": "https://images.unsplash.com/photo-1516767848735-fb701beb5567?ixlib=rb-1.2.1&q=80&fm=jpg&crop=entropy&cs=tinysrgb&w=200&fit=max&ixid=eyJhcHBfaWQiOjUyNzA0fQ"
      },
      "links": {
        "self": "https://api.unsplash.com/photos/pQwll5IG-I0",
        "html": "https://unsplash.com/photos/pQwll5IG-I0",
        "download": "https://unsplash.com/photos/pQwll5IG-I0/download",
        "download_location": "https://api.unsplash.com/photos/pQwll5IG-I0/download"
      },
      "categories": [],
      "sponsored": false,
      "sponsored_by": null,
      "sponsored_impressions_id": null,
      "likes": 155,
      "liked_by_user": false,
      "current_user_collections": [],
      "slug": "off-center",
      "user": {
        "id": "kt7ChDgBdYg",
        "updated_at": "2019-01-20T00:25:23-05:00",
        "username": "the_roaming_platypus",
        "name": "The Roaming Platypus",
        "first_name": "The Roaming Platypus",
        "last_name": null,
        "twitter_username": "timotaitun",
        "portfolio_url": null,
        "bio": "Mobile photography",
        "location": null,
        "links": {
          "self": "https://api.unsplash.com/users/the_roaming_platypus",
          "html": "https://unsplash.com/@the_roaming_platypus",
          "photos": "https://api.unsplash.com/users/the_roaming_platypus/photos",
          "likes": "https://api.unsplash.com/users/the_roaming_platypus/likes",
          "portfolio": "https://api.unsplash.com/users/the_roaming_platypus/portfolio",
          "following": "https://api.unsplash.com/users/the_roaming_platypus/following",
          "followers": "https://api.unsplash.com/users/the_roaming_platypus/followers"
        },
        "profile_image": {
          "small": "https://images.unsplash.com/profile-1495641006625-883a96c32e4d?ixlib=rb-1.2.1&q=80&fm=jpg&crop=faces&cs=tinysrgb&fit=crop&h=32&w=32",
          "medium": "https://images.unsplash.com/profile-1495641006625-883a96c32e4d?ixlib=rb-1.2.1&q=80&fm=jpg&crop=faces&cs=tinysrgb&fit=crop&h=64&w=64",
          "large": "https://images.unsplash.com/profile-1495641006625-883a96c32e4d?ixlib=rb-1.2.1&q=80&fm=jpg&crop=faces&cs=tinysrgb&fit=crop&h=128&w=128"
        },
        "instagram_username": "timjxsh",
        "total_collections": 5,
        "total_likes": 64,
        "total_photos": 44,
        "accepted_tos": true
      },
      "tags": [
        {
          "title": "cactus"
        },
        {
          "title": "spikes"
        },
        {
          "title": "plant"
        },
        {
          "title": "pot"
        },
        {
          "title": "planter"
        },
        {
          "title": "home"
        },
        {
          "title": "decor"
        },
        {
          "title": "indoor"
        },
        {
          "title": "houseplant"
        },
        {
          "title": "succulent"
        },
        {
          "title": "stones"
        },
        {
          "title": "white"
        },
        {
          "title": "food"
        },
        {
          "title": "beautiful"
        },
        {
          "title": "green"
        },
        {
          "title": "light"
        },
        {
          "title": "water"
        },
        {
          "title": "pasture"
        },
        {
          "title": "tissue"
        },
        {
          "title": "grass"
        }
      ],
      "photo_tags": [
        {
          "title": "cactus"
        },
        {
          "title": "spikes"
        },
        {
          "title": "plant"
        },
        {
          "title": "pot"
        },
        {
          "title": "planter"
        }
      ]
    },
    {
      "id": "rD2dc_2S3i0",
      "created_at": "2018-02-08T18:51:03-05:00",
      "updated_at": "2018-08-28T20:46:38-04:00",
      "width": 3024,
      "height": 4032,
      "color": "#0B0D13",
      "description": "red pencil on top of mathematical quiz paper",
      "urls": {
        "raw": "https://images.unsplash.com/photo-1518133835878-5a93cc3f89e5?ixlib=rb-1.2.1&ixid=eyJhcHBfaWQiOjUyNzA0fQ",
        "full": "https://images.unsplash.com/photo-1518133835878-5a93cc3f89e5?ixlib=rb-1.2.1&q=85&fm=jpg&crop=entropy&cs=srgb&ixid=eyJhcHBfaWQiOjUyNzA0fQ",
        "regular": "https://images.unsplash.com/photo-1518133835878-5a93cc3f89e5?ixlib=rb-1.2.1&q=80&fm=jpg&crop=entropy&cs=tinysrgb&w=1080&fit=max&ixid=eyJhcHBfaWQiOjUyNzA0fQ",
        "small": "https://images.unsplash.com/photo-1518133835878-5a93cc3f89e5?ixlib=rb-1.2.1&q=80&fm=jpg&crop=entropy&cs=tinysrgb&w=400&fit=max&ixid=eyJhcHBfaWQiOjUyNzA0fQ",
        "thumb": "https://images.unsplash.com/photo-1518133835878-5a93cc3f89e5?ixlib=rb-1.2.1&q=80&fm=jpg&crop=entropy&cs=tinysrgb&w=200&fit=max&ixid=eyJhcHBfaWQiOjUyNzA0fQ"
      },
      "links": {
        "self": "https://api.unsplash.com/photos/rD2dc_2S3i0",
        "html": "https://unsplash.com/photos/rD2dc_2S3i0",
        "download": "https://unsplash.com/photos/rD2dc_2S3i0/download",
        "download_location": "https://api.unsplash.com/photos/rD2dc_2S3i0/download"
      },
      "categories": [],
      "sponsored": false,
      "sponsored_by": null,
      "sponsored_impressions_id": null,
      "likes": 39,
      "liked_by_user": false,
      "current_user_collections": [],
      "slug": "exam",
      "user": {
        "id": "vm7k_1iG2Jw",
        "updated_at": "2019-01-22T08:56:08-05:00",
        "username": "chrisliverani",
        "name": "Chris Liverani",
        "first_name": "Chris",
        "last_name": "Liverani",
        "twitter_username": "chrisliverani",
        "portfolio_url": null,
        "bio": "Unsplash numbers guy // student at the @charlesdeluvio school of photography",
        "location": "Montreal, QC",
        "links": {
          "self": "https://api.unsplash.com/users/chrisliverani",
          "html": "https://unsplash.com/@chrisliverani",
          "photos": "https://api.unsplash.com/users/chrisliverani/photos",
          "likes": "https://api.unsplash.com/users/chrisliverani/likes",
          "portfolio": "https://api.unsplash.com/users/chrisliverani/portfolio",
          "following": "https://api.unsplash.com/users/chrisliverani/following",
          "followers": "https://api.unsplash.com/users/chrisliverani/followers"
        },
        "profile_image": {
          "small": "https://images.unsplash.com/profile-1542390524643-c5053b52fc98?ixlib=rb-1.2.1&q=80&fm=jpg&crop=faces&cs=tinysrgb&fit=crop&h=32&w=32",
          "medium": "https://images.unsplash.com/profile-1542390524643-c5053b52fc98?ixlib=rb-1.2.1&q=80&fm=jpg&crop=faces&cs=tinysrgb&fit=crop&h=64&w=64",
          "large": "https://images.unsplash.com/profile-1542390524643-c5053b52fc98?ixlib=rb-1.2.1&q=80&fm=jpg&crop=faces&cs=tinysrgb&fit=crop&h=128&w=128"
        },
        "instagram_username": null,
        "total_collections": 2,
        "total_likes": 200,
        "total_photos": 100,
        "accepted_tos": true
      },
      "tags": [
        {
          "title": "exam"
        },
        {
          "title": "pencil"
        },
        {
          "title": "math"
        },
        {
          "title": "multiplication"
        },
        {
          "title": "mathematic"
        },
        {
          "title": "calculation"
        },
        {
          "title": "computation"
        },
        {
          "title": "arithmetic"
        },
        {
          "title": "number"
        },
        {
          "title": "homework"
        },
        {
          "title": "study"
        },
        {
          "title": "academic"
        },
        {
          "title": "paper"
        },
        {
          "title": "error"
        },
        {
          "title": "exercise"
        },
        {
          "title": "calculu"
        }
      ],
      "photo_tags": [
        {
          "title": "exam"
        },
        {
          "title": "pencil"
        },
        {
          "title": "math"
        },
        {
          "title": "multiplication"
        },
        {
          "title": "mathematic"
        }
      ]
    },
    {
      "id": "3GZi6OpSDcY",
      "created_at": "2018-01-31T12:46:36-05:00",
      "updated_at": "2018-08-28T20:44:26-04:00",
      "width": 3888,
      "height": 2592,
      "color": "#E7E3DF",
      "description": "electronic circuit boards near tester",
      "urls": {
        "raw": "https://images.unsplash.com/photo-1517420704952-d9f39e95b43e?ixlib=rb-1.2.1&ixid=eyJhcHBfaWQiOjUyNzA0fQ",
        "full": "https://images.unsplash.com/photo-1517420704952-d9f39e95b43e?ixlib=rb-1.2.1&q=85&fm=jpg&crop=entropy&cs=srgb&ixid=eyJhcHBfaWQiOjUyNzA0fQ",
        "regular": "https://images.unsplash.com/photo-1517420704952-d9f39e95b43e?ixlib=rb-1.2.1&q=80&fm=jpg&crop=entropy&cs=tinysrgb&w=1080&fit=max&ixid=eyJhcHBfaWQiOjUyNzA0fQ",
        "small": "https://images.unsplash.com/photo-1517420704952-d9f39e95b43e?ixlib=rb-1.2.1&q=80&fm=jpg&crop=entropy&cs=tinysrgb&w=400&fit=max&ixid=eyJhcHBfaWQiOjUyNzA0fQ",
        "thumb": "https://images.unsplash.com/photo-1517420704952-d9f39e95b43e?ixlib=rb-1.2.1&q=80&fm=jpg&crop=entropy&cs=tinysrgb&w=200&fit=max&ixid=eyJhcHBfaWQiOjUyNzA0fQ"
      },
      "links": {
        "self": "https://api.unsplash.com/photos/3GZi6OpSDcY",
        "html": "https://unsplash.com/photos/3GZi6OpSDcY",
        "download": "https://unsplash.com/photos/3GZi6OpSDcY/download",
        "download_location": "https://api.unsplash.com/photos/3GZi6OpSDcY/download"
      },
      "categories": [],
      "sponsored": false,
      "sponsored_by": null,
      "sponsored_impressions_id": null,
      "likes": 93,
      "liked_by_user": false,
      "current_user_collections": [],
      "slug": "experimentation",
      "user": {
        "id": "yfTaopiEQ6Q",
        "updated_at": "2019-01-15T18:59:18-05:00",
        "username": "nicolasthomas",
        "name": "Nicolas Thomas",
        "first_name": "Nicolas",
        "last_name": "Thomas",
        "twitter_username": "nicolasth",
        "portfolio_url": "https://www.studio-lafayette.com",
        "bio": "Amateur photographer, digital & analog",
        "location": "Ecquevilly, France",
        "links": {
          "self": "https://api.unsplash.com/users/nicolasthomas",
          "html": "https://unsplash.com/@nicolasthomas",
          "photos": "https://api.unsplash.com/users/nicolasthomas/photos",
          "likes": "https://api.unsplash.com/users/nicolasthomas/likes",
          "portfolio": "https://api.unsplash.com/users/nicolasthomas/portfolio",
          "following": "https://api.unsplash.com/users/nicolasthomas/following",
          "followers": "https://api.unsplash.com/users/nicolasthomas/followers"
        },
        "profile_image": {
          "small": "https://images.unsplash.com/profile-1516824854869-bca0ed434a9b?ixlib=rb-1.2.1&q=80&fm=jpg&crop=faces&cs=tinysrgb&fit=crop&h=32&w=32",
          "medium": "https://images.unsplash.com/profile-1516824854869-bca0ed434a9b?ixlib=rb-1.2.1&q=80&fm=jpg&crop=faces&cs=tinysrgb&fit=crop&h=64&w=64",
          "large": "https://images.unsplash.com/profile-1516824854869-bca0ed434a9b?ixlib=rb-1.2.1&q=80&fm=jpg&crop=faces&cs=tinysrgb&fit=crop&h=128&w=128"
        },
        "instagram_username": "nicolasth",
        "total_collections": 0,
        "total_likes": 0,
        "total_photos": 100,
        "accepted_tos": false
      },
      "tags": [
        {
          "title": "science"
        },
        {
          "title": "electronic"
        },
        {
          "title": "experiment"
        },
        {
          "title": "electricity"
        },
        {
          "title": "laboratory"
        },
        {
          "title": "processor"
        },
        {
          "title": "resistor"
        },
        {
          "title": "wire"
        },
        {
          "title": "experience"
        },
        {
          "title": "scientific"
        },
        {
          "title": "wires"
        },
        {
          "title": "electric"
        },
        {
          "title": "technology"
        },
        {
          "title": "lab"
        },
        {
          "title": "engineering"
        },
        {
          "title": "chemicals"
        },
        {
          "title": "color"
        },
        {
          "title": "colour"
        },
        {
          "title": "ducation"
        },
        {
          "title": "learning"
        }
      ],
      "photo_tags": [
        {
          "title": "science"
        },
        {
          "title": "electronic"
        },
        {
          "title": "experiment"
        },
        {
          "title": "electricity"
        },
        {
          "title": "laboratory"
        }
      ]
    },
    {
      "id": "5fNmWej4tAA",
      "created_at": "2016-01-30T09:58:32-05:00",
      "updated_at": "2018-08-28T20:06:31-04:00",
      "width": 7360,
      "height": 4912,
      "color": "#043836",
      "description": "person holding pencil near laptop computer",
      "urls": {
        "raw": "https://images.unsplash.com/photo-1454165804606-c3d57bc86b40?ixlib=rb-1.2.1&ixid=eyJhcHBfaWQiOjUyNzA0fQ",
        "full": "https://images.unsplash.com/photo-1454165804606-c3d57bc86b40?ixlib=rb-1.2.1&q=85&fm=jpg&crop=entropy&cs=srgb&ixid=eyJhcHBfaWQiOjUyNzA0fQ",
        "regular": "https://images.unsplash.com/photo-1454165804606-c3d57bc86b40?ixlib=rb-1.2.1&q=80&fm=jpg&crop=entropy&cs=tinysrgb&w=1080&fit=max&ixid=eyJhcHBfaWQiOjUyNzA0fQ",
        "small": "https://images.unsplash.com/photo-1454165804606-c3d57bc86b40?ixlib=rb-1.2.1&q=80&fm=jpg&crop=entropy&cs=tinysrgb&w=400&fit=max&ixid=eyJhcHBfaWQiOjUyNzA0fQ",
        "thumb": "https://images.unsplash.com/photo-1454165804606-c3d57bc86b40?ixlib=rb-1.2.1&q=80&fm=jpg&crop=entropy&cs=tinysrgb&w=200&fit=max&ixid=eyJhcHBfaWQiOjUyNzA0fQ"
      },
      "links": {
        "self": "https://api.unsplash.com/photos/5fNmWej4tAA",
        "html": "https://unsplash.com/photos/5fNmWej4tAA",
        "download": "https://unsplash.com/photos/5fNmWej4tAA/download",
        "download_location": "https://api.unsplash.com/photos/5fNmWej4tAA/download"
      },
      "categories": [],
      "sponsored": false,
      "sponsored_by": null,
      "sponsored_impressions_id": null,
      "likes": 2607,
      "liked_by_user": false,
      "current_user_collections": [],
      "slug": "brainstorming-over-paper",
      "user": {
        "id": "nS8hxc6Omsg",
        "updated_at": "2019-01-22T23:58:19-05:00",
        "username": "helloquence",
        "name": "Helloquence",
        "first_name": "Helloquence",
        "last_name": null,
        "twitter_username": "helloquence",
        "portfolio_url": "http://helloquence.com/",
        "bio": "Web Agency ",
        "location": "Grenoble",
        "links": {
          "self": "https://api.unsplash.com/users/helloquence",
          "html": "https://unsplash.com/@helloquence",
          "photos": "https://api.unsplash.com/users/helloquence/photos",
          "likes": "https://api.unsplash.com/users/helloquence/likes",
          "portfolio": "https://api.unsplash.com/users/helloquence/portfolio",
          "following": "https://api.unsplash.com/users/helloquence/following",
          "followers": "https://api.unsplash.com/users/helloquence/followers"
        },
        "profile_image": {
          "small": "https://images.unsplash.com/profile-1454062790943-809d24ff9bc9?ixlib=rb-1.2.1&q=80&fm=jpg&crop=faces&cs=tinysrgb&fit=crop&h=32&w=32",
          "medium": "https://images.unsplash.com/profile-1454062790943-809d24ff9bc9?ixlib=rb-1.2.1&q=80&fm=jpg&crop=faces&cs=tinysrgb&fit=crop&h=64&w=64",
          "large": "https://images.unsplash.com/profile-1454062790943-809d24ff9bc9?ixlib=rb-1.2.1&q=80&fm=jpg&crop=faces&cs=tinysrgb&fit=crop&h=128&w=128"
        },
        "instagram_username": "wearehelloquence ",
        "total_collections": 0,
        "total_likes": 0,
        "total_photos": 4,
        "accepted_tos": false
      },
      "tags": [
        {
          "title": "computer"
        },
        {
          "title": "work"
        },
        {
          "title": "paper"
        },
        {
          "title": "brainstorming"
        },
        {
          "title": "workspace"
        },
        {
          "title": "keyboard"
        },
        {
          "title": "notebook"
        },
        {
          "title": "man"
        },
        {
          "title": "button"
        },
        {
          "title": "male"
        },
        {
          "title": "screen"
        },
        {
          "title": "finger"
        },
        {
          "title": "pencil"
        },
        {
          "title": "laptop"
        },
        {
          "title": "mac"
        },
        {
          "title": "person"
        },
        {
          "title": "desk"
        },
        {
          "title": "meeting"
        },
        {
          "title": "working"
        },
        {
          "title": "math"
        }
      ],
      "photo_tags": [
        {
          "title": "computer"
        },
        {
          "title": "work"
        },
        {
          "title": "paper"
        },
        {
          "title": "brainstorming"
        },
        {
          "title": "workspace"
        }
      ]
    },
    {
      "id": "KTzZVDjUsXw",
      "created_at": "2017-08-24T17:38:24-04:00",
      "updated_at": "2018-08-28T20:21:04-04:00",
      "width": 6024,
      "height": 4024,
      "color": "#EFF3EB",
      "description": "person holding rectangular black wooden photo frame with Give. Thanks. print",
      "urls": {
        "raw": "https://images.unsplash.com/photo-1503610594381-aed30c818b8e?ixlib=rb-1.2.1&ixid=eyJhcHBfaWQiOjUyNzA0fQ",
        "full": "https://images.unsplash.com/photo-1503610594381-aed30c818b8e?ixlib=rb-1.2.1&q=85&fm=jpg&crop=entropy&cs=srgb&ixid=eyJhcHBfaWQiOjUyNzA0fQ",
        "regular": "https://images.unsplash.com/photo-1503610594381-aed30c818b8e?ixlib=rb-1.2.1&q=80&fm=jpg&crop=entropy&cs=tinysrgb&w=1080&fit=max&ixid=eyJhcHBfaWQiOjUyNzA0fQ",
        "small": "https://images.unsplash.com/photo-1503610594381-aed30c818b8e?ixlib=rb-1.2.1&q=80&fm=jpg&crop=entropy&cs=tinysrgb&w=400&fit=max&ixid=eyJhcHBfaWQiOjUyNzA0fQ",
        "thumb": "https://images.unsplash.com/photo-1503610594381-aed30c818b8e?ixlib=rb-1.2.1&q=80&fm=jpg&crop=entropy&cs=tinysrgb&w=200&fit=max&ixid=eyJhcHBfaWQiOjUyNzA0fQ"
      },
      "links": {
        "self": "https://api.unsplash.com/photos/KTzZVDjUsXw",
        "html": "https://unsplash.com/photos/KTzZVDjUsXw",
        "download": "https://unsplash.com/photos/KTzZVDjUsXw/download",
        "download_location": "https://api.unsplash.com/photos/KTzZVDjUsXw/download"
      },
      "categories": [],
      "sponsored": false,
      "sponsored_by": null,
      "sponsored_impressions_id": null,
      "likes": 900,
      "liked_by_user": false,
      "current_user_collections": [],
      "slug": "signs-of-gratitude",
      "user": {
        "id": "YRa3cOINidE",
        "updated_at": "2019-01-24T06:49:49-05:00",
        "username": "simonmaage",
        "name": "Simon Maage",
        "first_name": "Simon",
        "last_name": "Maage",
        "twitter_username": null,
        "portfolio_url": null,
        "bio": null,
        "location": "Germany",
        "links": {
          "self": "https://api.unsplash.com/users/simonmaage",
          "html": "https://unsplash.com/@simonmaage",
          "photos": "https://api.unsplash.com/users/simonmaage/photos",
          "likes": "https://api.unsplash.com/users/simonmaage/likes",
          "portfolio": "https://api.unsplash.com/users/simonmaage/portfolio",
          "following": "https://api.unsplash.com/users/simonmaage/following",
          "followers": "https://api.unsplash.com/users/simonmaage/followers"
        },
        "profile_image": {
          "small": "https://images.unsplash.com/profile-1503396750155-2180dc42a476?ixlib=rb-1.2.1&q=80&fm=jpg&crop=faces&cs=tinysrgb&fit=crop&h=32&w=32",
          "medium": "https://images.unsplash.com/profile-1503396750155-2180dc42a476?ixlib=rb-1.2.1&q=80&fm=jpg&crop=faces&cs=tinysrgb&fit=crop&h=64&w=64",
          "large": "https://images.unsplash.com/profile-1503396750155-2180dc42a476?ixlib=rb-1.2.1&q=80&fm=jpg&crop=faces&cs=tinysrgb&fit=crop&h=128&w=128"
        },
        "instagram_username": null,
        "total_collections": 0,
        "total_likes": 32,
        "total_photos": 20,
        "accepted_tos": false
      },
      "tags": [
        {
          "title": "poster"
        },
        {
          "title": "sign"
        },
        {
          "title": "art"
        },
        {
          "title": "print"
        },
        {
          "title": "text"
        },
        {
          "title": "words"
        },
        {
          "title": "tumblr"
        },
        {
          "title": "wallpaper"
        },
        {
          "title": "hands"
        },
        {
          "title": "holding"
        },
        {
          "title": "thanks"
        },
        {
          "title": "give"
        },
        {
          "title": "field"
        },
        {
          "title": "grass"
        },
        {
          "title": "tree"
        },
        {
          "title": "frame"
        },
        {
          "title": "bokeh"
        },
        {
          "title": "blur"
        },
        {
          "title": "thank"
        },
        {
          "title": "thanksgiving"
        }
      ],
      "photo_tags": [
        {
          "title": "poster"
        },
        {
          "title": "sign"
        },
        {
          "title": "art"
        },
        {
          "title": "print"
        },
        {
          "title": "text"
        }
      ]
    }
  ]
}